pymosa_mimosa26_interpreter/__init__.py
pymosa_mimosa26_interpreter/data_interpreter.py
pymosa_mimosa26_interpreter/plotting.py
pymosa_mimosa26_interpreter/raw_data_interpreter.py
pymosa_mimosa26_interpreter/testing/__init__.py
pymosa_mimosa26_interpreter/testing/test_interpreter.py
pymosa_mimosa26_interpreter/testing/test_raw_chunk_size.py
pymosa_mimosa26_interpreter/testing/tools/__init__.py
pymosa_mimosa26_interpreter/testing/tools/test_tools.py
pymosa_mimosa26_interpreter-1.1.0.dist-info/LICENSE.txt
pymosa_mimosa26_interpreter-1.1.0.dist-info/METADATA
pymosa_mimosa26_interpreter-1.1.0.dist-info/WHEEL
pymosa_mimosa26_interpreter-1.1.0.dist-info/top_level.txt
pymosa_mimosa26_interpreter-1.1.0.dist-info/RECORD
